IAPWS97.py
fixed_format_file.py
geometry.py
mulgrids.py
t2data.py
t2grids.py
t2incons.py
t2listing.py
t2thermo.py
pytough-1.6.5.dist-info/licenses/LICENSE
pytough-1.6.5.dist-info/METADATA
pytough-1.6.5.dist-info/WHEEL
pytough-1.6.5.dist-info/top_level.txt
pytough-1.6.5.dist-info/RECORD
