Metadata-Version: 2.4
Name: PyTOUGH
Version: 1.6.5
Summary: Python scripting library for TOUGH2 simulation
Author-email: Adrian Croucher <a.croucher@auckland.ac.nz>
License:                    GNU LESSER GENERAL PUBLIC LICENSE
Project-URL: repository, https://github.com/acroucher/PyTOUGH
Classifier: Programming Language :: Python :: 2
Classifier: Programming Language :: Python :: 3
Classifier: License :: OSI Approved :: GNU Lesser General Public License v3 (LGPLv3)
Classifier: Operating System :: OS Independent
Requires-Python: >=2.7
License-File: LICENSE
Requires-Dist: numpy
Requires-Dist: scipy
Requires-Dist: matplotlib
Dynamic: license-file
